{"3UYh7vpTjSo_0": {"annotations": {"label": "right", "segment": [371.6, 375.6]}, "annotations_frame": {"label": "right", "segment": [9290.0, 9390.0]}, "annotations_rounded": {"label": "right", "segment": [371.0, 376.0]}, "duration": 4.0, "duration_frame": 100.0, "duration_rounded": 5.0, "subset": "train", "url": "https://www.youtube.com/watch?v=3UYh7vpTjSo"}, "3UYh7vpTjSo_1": {"annotations": {"label": "together", "segment": [542.16, 546.16]}, "annotations_frame": {"label": "together", "segment": [13554.0, 13654.0]}, "annotations_rounded": {"label": "together", "segment": [542.0, 547.0]}, "duration": 4.0, "duration_frame": 100.0, "duration_rounded": 5.0, "subset": "train", "url": "https://www.youtube.com/watch?v=3UYh7vpTjSo"}, "3UYh7vpTjSo_2": {"annotations": {"label": "left", "segment": [589.64, 593.64]}, "annotations_frame": {"label": "left", "segment": [14741.0, 14841.0]}, "annotations_rounded": {"label": "left", "segment": [589.0, 594.0]}, "duration": 4.0, "duration_frame": 100.0, "duration_rounded": 5.0, "subset": "train", "url": "https://www.youtube.com/watch?v=3UYh7vpTjSo"}, "3UYh7vpTjSo_3": {"annotations": {"label": "left", "segment": [609.96, 613.96]}, "annotations_frame": {"label": "left", "segment": [15249.0, 15349.0]}, "annotations_rounded": {"label": "left", "segment": [609.0, 614.0]}, "duration": 4.0, "duration_frame": 100.0, "duration_rounded": 5.0, "subset": "train", "url": "https://www.youtube.com/watch?v=3UYh7vpTjSo"}, "3UYh7vpTjSo_4": {"annotations": {"label": "left", "segment": [644.2, 648.2]}, "annotations_frame": {"label": "left", "segment": [16105.0, 16205.0]}, "annotations_rounded": {"label": "left", "segment": [644.0, 649.0]}, "duration": 4.0, "duration_frame": 100.0, "duration_rounded": 5.0, "subset": "train", "url": "https://www.youtube.com/watch?v=3UYh7vpTjSo"}, "3UYh7vpTjSo_5": {"annotations": {"label": "left", "segment": [692.2, 696.2]}, "annotations_frame": {"label": "left", "segment": [17305.0, 17405.0]}, "annotations_rounded": {"label": "left", "segment": [692.0, 697.0]}, "duration": 4.0, "duration_frame": 100.0, "duration_rounded": 5.0, "subset": "train", "url": "https://www.youtube.com/watch?v=3UYh7vpTjSo"}, "3UYh7vpTjSo_6": {"annotations": {"label": "right", "segment": [724.84, 728.84]}, "annotations_frame": {"label": "right", "segment": [18121.0, 18221.0]}, "annotations_rounded": {"label": "right", "segment": [724.0, 729.0]}, "duration": 4.0, "duration_frame": 100.0, "duration_rounded": 5.0, "subset": "train", "url": "https://www.youtube.com/watch?v=3UYh7vpTjSo"}}